LICENSE
MANIFEST.in
README.rst
setup.py
django_db_log.egg-info/PKG-INFO
django_db_log.egg-info/SOURCES.txt
django_db_log.egg-info/dependency_links.txt
django_db_log.egg-info/top_level.txt
djangodblog/__init__.py
djangodblog/admin.py
djangodblog/handlers.py
djangodblog/helpers.py
djangodblog/manager.py
djangodblog/middleware.py
djangodblog/models.py
djangodblog/routers.py
djangodblog/settings.py
djangodblog/utils.py
djangodblog/management/__init__.py
djangodblog/management/commands/__init__.py
djangodblog/management/commands/cleanup_dblog.py
djangodblog/migrations/0001_initial.py
djangodblog/migrations/0002_update_indexes.py
djangodblog/migrations/0003_add_error_checksum.py
djangodblog/migrations/0004_fill_error_checksums.py
djangodblog/migrations/__init__.py
djangodblog/templates/admin/djangodblog/error/change_form.html
djangodblog/templates/admin/djangodblog/error/change_list.html
djangodblog/templates/admin/djangodblog/errorbatch/change_form.html
djangodblog/templates/admin/djangodblog/errorbatch/change_list.html
djangodblog/templates/admin/djangodblog/errorbatch/change_list_results.html
djangodblog/templates/admin/djangodblog/partials/change_list_styles.html
djangodblog/templatetags/__init__.py
djangodblog/templatetags/dblog_admin.py
djangodblog/tests/__init__.py
djangodblog/tests/models.py
djangodblog/tests/tests.py
djangodblog/tests/urls.py
djangodblog/tests/views.py