Metadata-Version: 1.0
Name: django-db-log
Version: 2.1.8
Summary: Exception Logging to a Database in Django
Home-page: http://github.com/dcramer/django-db-log
Author: David Cramer
Author-email: dcramer@gmail.com
License: UNKNOWN
Platform: UNKNOWN
Classifier: Framework :: Django
Classifier: Intended Audience :: Developers
Classifier: Intended Audience :: System Administrators
Classifier: Operating System :: OS Independent
Classifier: Topic :: Software Development
